zeonaqapi/__init__.py
zeonaqapi/client.py
zeonaqapi-1.0.9.dist-info/LICENSE
zeonaqapi-1.0.9.dist-info/METADATA
zeonaqapi-1.0.9.dist-info/WHEEL
zeonaqapi-1.0.9.dist-info/top_level.txt
zeonaqapi-1.0.9.dist-info/RECORD
