Metadata-Version: 2.1
Name: zeonaqapi
Version: 1.0.9
Summary: An API client library for the ZeonAQ API.
Home-page: https://github.com/darkhorsestech/zeonaqapi
Author: Craig Carmichael
Author-email: operations@darkhorsestech.com
License: MIT
License-File: LICENSE
Requires-Dist: requests
Requires-Dist: pandas
Requires-Dist: monsterapi
Requires-Dist: openai
